hysteresis_area_idz/__init__.py
hysteresis_area_idz/__main__.py
hysteresis_area_idz-0.7.0.dist-info/WHEEL
hysteresis_area_idz-0.7.0.dist-info/METADATA
hysteresis_area_idz-0.7.0.dist-info/RECORD
